vsm_jwetzel/__init__.py
vsm_jwetzel/add.py
vsm_jwetzel/subtract.py
vsm_jwetzel/extras/__init__.py
vsm_jwetzel/extras/divide.py
vsm_jwetzel/extras/multiply.py
vsm_jwetzel-0.0.4.dist-info/METADATA
vsm_jwetzel-0.0.4.dist-info/WHEEL
vsm_jwetzel-0.0.4.dist-info/top_level.txt
vsm_jwetzel-0.0.4.dist-info/RECORD
